tests/__init__.py
tests/tests.py
tfwatcher/__init__.py
tfwatcher/firebase_config.py
tfwatcher/firebase_helpers.py
tfwatcher/version.py
tfwatcher/callbacks/__init__.py
tfwatcher/callbacks/epoch.py
tfwatcher/callbacks/predict.py
tfwatcher/callbacks/predict_batch.py
tfwatcher/callbacks/test_batch.py
tfwatcher/callbacks/train_batch.py
tf_watcher-0.1.2.dist-info/LICENSE
tf_watcher-0.1.2.dist-info/METADATA
tf_watcher-0.1.2.dist-info/WHEEL
tf_watcher-0.1.2.dist-info/top_level.txt
tf_watcher-0.1.2.dist-info/RECORD
